reversible/__init__.py
reversible/core.py
reversible/generator.py
reversible/tornado/__init__.py
reversible/tornado/core.py
reversible/tornado/generator.py
reversible-0.2.0.dist-info/DESCRIPTION.rst
reversible-0.2.0.dist-info/METADATA
reversible-0.2.0.dist-info/metadata.json
reversible-0.2.0.dist-info/RECORD
reversible-0.2.0.dist-info/top_level.txt
reversible-0.2.0.dist-info/WHEEL
