Metadata-Version: 2.0
Name: reversible
Version: 0.2.0
Summary: A Python library to represent, construct, chain, and execute reversible actions.
Home-page: https://github.com/abhinav/reversible
Author: Abhinav Gupta
Author-email: mail@abhinavg.net
License: MIT
Platform: UNKNOWN
Classifier: Development Status :: 4 - Beta
Classifier: Intended Audience :: Developers
Classifier: License :: OSI Approved :: MIT License
Classifier: Programming Language :: Python
Classifier: Programming Language :: Python :: 3
Classifier: Topic :: Software Development :: Libraries :: Python Modules
Provides-Extra: tornado
Requires-Dist: tornado; extra == 'tornado'
Requires-Dist: greenlet; extra == 'tornado'
